[
    {
        "id":"0",
        "title": "AMD - Athom",
        "description":"Lorem ipsum dolor sit amet consectetur adipisicing elit. Laudantium repellendus rerum, mollitia cupiditate explicabo, fugit ratione, ipsam officiis ducimus sit voluptatem dolor ipsum ut suscipit ex vitae vel odit esse.",
        "price": 8000,
        "pictureUrl": "http://localhost:3000/Images/Athom.png",
        "stock": 20,
        "categoria": 1,
        "to":"0"
    },
    {
        "id":"1",
        "title": "AMD - ryzen3",
        "description":"Lorem ipsum dolor sit amet consectetur adipisicing elit. Laudantium repellendus rerum, mollitia cupiditate explicabo, fugit ratione, ipsam officiis ducimus sit voluptatem dolor ipsum ut suscipit ex vitae vel odit esse.",
        "price": 12000,
        "pictureUrl":"http://localhost:3000/Images/ryzen3.png",
        "stock": 30,
        "categoria": 1,
        "to":"1"
    },
    {
        "id":"2",
        "title": "AMD - ryzen5",
        "description":"Lorem ipsum dolor sit amet consectetur adipisicing elit. Laudantium repellendus rerum, mollitia cupiditate explicabo, fugit ratione, ipsam officiis ducimus sit voluptatem dolor ipsum ut suscipit ex vitae vel odit esse." ,
        "price": 22000,
        "pictureUrl":"http://localhost:3000/Images/ryzen5.png",
        "stock": 40,
        "categoria": 1,
        "to":"2"
    },
    {
        "id":"3",
        "title": "AMD - ryzen7",
        "description":"Lorem ipsum dolor sit amet consectetur adipisicing elit. Laudantium repellendus rerum, mollitia cupiditate explicabo, fugit ratione, ipsam officiis ducimus sit voluptatem dolor ipsum ut suscipit ex vitae vel odit esse.",
        "price": 32000,
        "pictureUrl":"http://localhost:3000/Images/ryzen7.png",
        "stock": 40,
        "categoria": 1,
        "to":"3"
    }
]